[
  {
    "NCR_Number": "TSFS-AGMK-NCR-0001",
    "Project": "Освоения месторождения Ешлик-1 \r\nСтроительства комплекса медно-обогатительной фабрики (МОФ-3) с полным технологическим циклом производства.Хвостовое Хозяйство Карта №1\r\n",
    "Contractor": "Enter Engineering",
    "technical_supervisor_company": "ПО АГМК",
    "Discipline": "CIV",
    "major_object": "Магистральный пульповода хвостов карты 1",
    "Draw_number": "N/A",
    "Location": "Фундамент ФМ-2",
    "Procedure": "ППР TSFS-EE-000000-CIV-MET-0004",
    "NCR_Description": "В ходе операционного контроля на начальном участке магистрального пульповода (от ПК 0+00 по ПК 01+54) выявлены сколы фундамента ФМ-2 допущенные при монтаже металлоконструкций эстакады. Не выполнены обследования, не составлен дефектный акт, не производилась оценка прочности, не выполнены ремонтные работы по восстановлению фундамента.",
    "NCR_grade": "Очень важный",
    "inspection_date": "2025-05-08",
    "Correction_acts": "Подрядчику:1.\tНеобходимо обследовать фундамент ФМ-2, составить дефектный акт, произвести оценку прочности, произвести ремонт фундамента согласно процедуре MOF3-EE-000000-QAC-PRO-0006, предоставить протокол испытания ремонтного раствора.",
    "closed_date.plan": "2025-05-18",
    "closed_date.actual": "",
    "Measures": "Ремонт",
    "inspector_name_field": "Adilzhanov M",
    "NCR_Status": "Открыто",
    "inspector_id": 4,
    "inspector_name": "Doniyorkhon Rasulov",
    "photos": [
      "ncr_1_1.png"
    ],
    "id": 1,
    "created_at": "2026-01-27 13:09:30",
    "updated_at": "2026-01-28T22:58:32.010122"
  },
  {
    "NCR_Number": "TSFS-AGMK-NCR-002",
    "Project": "Освоения месторождения Ешлик-1 \r\nСтроительства комплекса медно-обогатительной фабрики (МОФ-3) с полным технологическим циклом производства.Хвостовое Хозяйство Карта №1\r\n",
    "Contractor": "Enter Engineering",
    "technical_supervisor_company": "PO AGMK",
    "Discipline": "CIV",
    "major_object": "Распределительный пульповод",
    "Draw_number": "П-359659-ХХ",
    "Location": "Промежуточные опоры - 1600",
    "Procedure": "ШНК 3.01.01-03 «Организация строительного производства» п.3",
    "NCR_Description": "Ведутся работы по изготовлению фундаментов промежуточных опор(ПО1600) распределительно пульповода без утвержденного ППР и технологической карты.",
    "NCR_grade": "Очень важный",
    "inspection_date": "2025-05-09",
    "Correction_acts": "1.\tНеобходимо предоставить утвержденный ППР на СМР по объекту «Распределительный пульповод»",
    "closed_date.plan": "2025-05-19",
    "closed_date.actual": "",
    "Measures": "Доработка",
    "inspector_name_field": "Адилжанов М",
    "NCR_Status": "Закрыто",
    "inspector_id": 4,
    "inspector_name": "Doniyorkhon Rasulov",
    "photos": [
      "ncr_2_1.png"
    ],
    "id": 2,
    "created_at": "2026-01-27 13:27:35",
    "signed_scan_url": "https://poagmk.sharepoint.com/sites/xx/Shared%20Documents/3.%20TSF%20reports/%D0%A4%D0%B0%D0%B9%D0%BB%D1%8B%20%D0%BF%D0%BE%20%D0%A2%D0%9D/%D0%9F%D1%80%D0%B5%D0%B4%D0%BF%D0%B8%D1%81%D0%B0%D0%BD%D0%B8%D1%8F/%D0%A1%D0%BA%D0%B0%D0%BD%D1%8B%20%D0%BF%D1%80%D0%B5%D0%B4%D0%BF%D0%B8%D1%81%D0%B0%D0%BD%D0%B8%D1%8F/%D0%97%D0%B0%D0%BA%D1%80%D1%8B%D1%82%D1%8B%D0%B5%20%D0%BF%D1%80%D0%B5%D0%B4%D0%BF%D0%B8%D1%81%D0%B0%D0%BD%D0%B8%D1%8F/%D0%97%D0%B0%D0%BA%D1%80%D1%8B%D1%82%D0%BE%D0%B5%20%D0%BF%D1%80%D0%B5%D0%B4%D0%BF%D0%B8%D1%81%D0%B0%D0%BD%D0%B8%D0%B5%20%E2%84%96TSFS-AGMK-NCR-002.pdf?csf=1&web=1&e=tc8gGn",
    "signed_scan_uploaded_at": "2026-01-27T17:17:25.895347",
    "signed_scan_uploaded_by": "Александр Тен",
    "updated_at": "2026-01-27T17:17:25.895808"
  },
  {
    "NCR_Number": "TSFS-AGMK-NCR-003",
    "Project": "Освоения месторождения Ешлик-1 \r\nСтроительства комплекса медно-обогатительной фабрики (МОФ-3) с полным технологическим циклом производства.Хвостовое Хозяйство Карта №1\r\n",
    "Contractor": "Enter Engineering",
    "technical_supervisor_company": "ПО АГМК",
    "Discipline": "CIV",
    "major_object": "Площадка подстанции ГПП-1 110/10кВ. ГПП-1 ПС 110/6 кВ - 2х10000",
    "Draw_number": "N/A",
    "Location": "Площадка подстанции ГПП",
    "Procedure": "ШНК 3.01.01-03 «Организация строительного производства» п.3",
    "NCR_Description": "Площадка подстанции ГПП-1 110/10кВ. ГПП-1 ПС 110/6 кВ - 2х10000, ведутся земляные работы без утвержденного ППР.",
    "NCR_grade": "Очень важный",
    "inspection_date": "2025-06-08",
    "Correction_acts": "1.\tНеобходимо предоставить утвержденный ППР на СМР по объекту «Площадка подстанции ГПП-1 110/10кВ. ГПП-1 ПС 110/6 кВ - 2х10000»",
    "closed_date.plan": "2026-06-19",
    "closed_date.actual": "",
    "Measures": "Доработка",
    "inspector_name_field": "Адилжанов М",
    "NCR_Status": "Закрыто",
    "inspector_id": 4,
    "inspector_name": "Doniyorkhon Rasulov",
    "photos": [],
    "id": 3,
    "created_at": "2026-01-27 13:30:07",
    "signed_scan_url": "https://poagmk.sharepoint.com/sites/xx/Shared%20Documents/3.%20TSF%20reports/%D0%A4%D0%B0%D0%B9%D0%BB%D1%8B%20%D0%BF%D0%BE%20%D0%A2%D0%9D/%D0%9F%D1%80%D0%B5%D0%B4%D0%BF%D0%B8%D1%81%D0%B0%D0%BD%D0%B8%D1%8F/%D0%A1%D0%BA%D0%B0%D0%BD%D1%8B%20%D0%BF%D1%80%D0%B5%D0%B4%D0%BF%D0%B8%D1%81%D0%B0%D0%BD%D0%B8%D1%8F/%D0%97%D0%B0%D0%BA%D1%80%D1%8B%D1%82%D1%8B%D0%B5%20%D0%BF%D1%80%D0%B5%D0%B4%D0%BF%D0%B8%D1%81%D0%B0%D0%BD%D0%B8%D1%8F/%D0%97%D0%B0%D0%BA%D1%80%D1%8B%D1%82%D0%BE%D0%B5%20%D0%BF%D1%80%D0%B5%D0%B4%D0%BF%D0%B8%D1%81%D0%B0%D0%BD%D0%B8%D0%B5%20%E2%84%96TSFS-AGMK-NCR-003.pdf?csf=1&web=1&e=oaWJWw",
    "signed_scan_uploaded_at": "2026-01-27T17:52:28.996003",
    "signed_scan_uploaded_by": "Александр Тен",
    "updated_at": "2026-01-27T17:52:28.996462"
  },
  {
    "NCR_Number": "TSFS-AGMK-NCR-004",
    "Project": "Освоения месторождения Ешлик-1 \r\nСтроительства комплекса медно-обогатительной фабрики (МОФ-3) с полным технологическим циклом производства.Хвостовое Хозяйство Карта №1\r\n",
    "Contractor": "Enter Engineering",
    "technical_supervisor_company": "ПО АГМК",
    "Discipline": "CIV",
    "major_object": "Магистральный пульповода хвостов карты 1",
    "Draw_number": "N/A",
    "Location": "Фундаменты промежуточных опор-1600",
    "Procedure": "ППР TSFS-EE-000000-CIV-MET-0004",
    "NCR_Description": "В ходе операционного контроля на начальном участке магистрального пульповода DN1600  от ПК 0+00 по ПК09+00 выявлены сколы фундаментов ПО 1600 с оголением арматуры. Не выполнены обследования, не составлен дефектный акт, не производилась оценка прочности, не выполнены ремонтные работы по восстановлению фундамента.",
    "NCR_grade": "Очень важный",
    "inspection_date": "2025-06-08",
    "Correction_acts": "1.\tОбследовать фундамент ПО-1600 составить дефектный акт, произвести оценку прочности, произвести ремонт фундамента согласно процедуре MOF3-EE-000000-QAC-PRO-0006, предоставить протокол испытания ремонтного раствора.",
    "closed_date.plan": "2025-06-18",
    "closed_date.actual": "",
    "Measures": "Ремонт",
    "inspector_name_field": "Адилжанов М",
    "NCR_Status": "Открыто",
    "inspector_id": 4,
    "inspector_name": "Doniyorkhon Rasulov",
    "photos": [
      "ncr_4_1.png"
    ],
    "id": 4,
    "created_at": "2026-01-27 13:34:10",
    "updated_at": "2026-01-28T22:58:16.994477"
  },
  {
    "NCR_Number": "TSFS-AGMK-NCR-005",
    "Project": "Освоения месторождения Ешлик-1 \r\nСтроительства комплекса медно-обогатительной фабрики (МОФ-3) с полным технологическим циклом производства.Хвостовое Хозяйство Карта №1\r\n",
    "Contractor": "Enter Engineering",
    "technical_supervisor_company": "ПО АГМК",
    "Discipline": "CIV",
    "major_object": "Магистральный пульповода хвостов карты 1",
    "Draw_number": "N/A",
    "Location": "Фундаменты ПО-1600, фундаменты для задвижек 1400/1600",
    "Procedure": "ППР TSFS-EE-000000-CIV-MET-0004",
    "NCR_Description": "Фундаменты ПО-1600, фундаменты для задвижек 1400/1600 узла переключения (16шт) были распалублены и транспортированы без оценки прочности.",
    "NCR_grade": "Очень важный",
    "inspection_date": "2025-06-08",
    "Correction_acts": "Подрядчику:1.\tПроизвести обследования фундаментов2.\tПроизвести операционный контроль прочности3.\tПредоставить протокола испытания на прочность бетонных изделий",
    "closed_date.plan": "2025-06-18",
    "closed_date.actual": "",
    "Measures": "Доработка",
    "inspector_name_field": "Адилжанов М.А",
    "NCR_Status": "Открыто",
    "inspector_id": 4,
    "inspector_name": "Doniyorkhon Rasulov",
    "photos": [
      "ncr_5_1.png"
    ],
    "id": 5,
    "created_at": "2026-01-27 13:36:43",
    "updated_at": "2026-01-28T22:57:57.442021"
  },
  {
    "NCR_Number": "TSFS-AGMK-NCR-006",
    "Project": "Освоения месторождения Ешлик-1 \r\nСтроительства комплекса медно-обогатительной фабрики (МОФ-3) с полным технологическим циклом производства.Хвостовое Хозяйство Карта №1\r\n",
    "Contractor": "Enter Engineering",
    "technical_supervisor_company": "ПО АГМК",
    "Discipline": "CIV",
    "major_object": "Магистральный пульповод хвостов карты 1",
    "Draw_number": "Д.3303-П-364176-АС/изм1,2",
    "Location": "фундамента ФМ-2",
    "Procedure": "ППР TSFS-EE-000000-CIV-MET-0004",
    "NCR_Description": "На эстакаде начального участка магистрального пульповода производится вырезка без согласования с проектной организацией и без выполнения необходимых расчётов фундамента ФМ-2",
    "NCR_grade": "Очень важный",
    "inspection_date": "2025-10-11",
    "Correction_acts": "\r\nПодрядчику:\r\n1.\tПроизвести расчеты прочности, устойчивости, несущей способности фундамента\r\n2.\tПроизвести техническое решение на изменение конструктива фундамента ФМ-2 с согласованием от проектного института\r\n3.\tПредоставить копию согласованного технического решения\r\n",
    "closed_date.plan": "2025-10-21",
    "closed_date.actual": "",
    "Measures": "Доработка",
    "inspector_name_field": "Адилжанов М.А",
    "NCR_Status": "Открыто",
    "inspector_id": 4,
    "inspector_name": "Doniyorkhon Rasulov",
    "photos": [
      "ncr_6_1.png",
      "ncr_6_2.png"
    ],
    "id": 6,
    "created_at": "2026-01-27 13:39:55"
  },
  {
    "NCR_Number": "TSFS-AGMK-NCR-007",
    "Project": "Освоения месторождения Ешлик-1 Строительства комплекса медно-обогатительной фабрики (МОФ-3) с полным технологическим циклом производства",
    "Contractor": "Enter Engineering Pte. Ltd.",
    "technical_supervisor_company": "ПО АГМК",
    "Discipline": "CIV",
    "major_object": "Участок водозабора",
    "Draw_number": "Д.3164-П-359168-ХХ",
    "Location": "Участок водозабора",
    "Procedure": "ШНК 3.01.01-03 «Организация строительного производства» п.3",
    "NCR_Description": "Карта 1. Участок водозабора, ведутся земляные работы без утвержденного ППР. осуществляющий",
    "NCR_grade": "Очень важный",
    "inspection_date": "2025-10-15",
    "Correction_acts": "Подрядчику:1.\tНеобходимо предоставить утвержденный ППР на СМР по объекту «Карта 1. Чаша хвостохранилища. Участок водозабора»",
    "closed_date.plan": "2025-10-25",
    "closed_date.actual": "",
    "Measures": "Доработка",
    "inspector_name_field": "Адилжанов М.А",
    "NCR_Status": "Закрыто",
    "inspector_id": 4,
    "inspector_name": "Doniyorkhon Rasulov",
    "photos": [
      "ncr_7_1.png",
      "ncr_7_2.png"
    ],
    "id": 7,
    "created_at": "2026-01-27 13:43:03",
    "signed_scan_url": "https://poagmk.sharepoint.com/sites/xx/Shared%20Documents/3.%20TSF%20reports/%D0%A4%D0%B0%D0%B9%D0%BB%D1%8B%20%D0%BF%D0%BE%20%D0%A2%D0%9D/%D0%9F%D1%80%D0%B5%D0%B4%D0%BF%D0%B8%D1%81%D0%B0%D0%BD%D0%B8%D1%8F/%D0%A1%D0%BA%D0%B0%D0%BD%D1%8B%20%D0%BF%D1%80%D0%B5%D0%B4%D0%BF%D0%B8%D1%81%D0%B0%D0%BD%D0%B8%D1%8F/%D0%97%D0%B0%D0%BA%D1%80%D1%8B%D1%82%D1%8B%D0%B5%20%D0%BF%D1%80%D0%B5%D0%B4%D0%BF%D0%B8%D1%81%D0%B0%D0%BD%D0%B8%D1%8F/%D0%97%D0%B0%D0%BA%D1%80%D1%8B%D1%82%D0%BE%D0%B5%20%D0%BF%D1%80%D0%B5%D0%B4%D0%BF%D0%B8%D1%81%D0%B0%D0%BD%D0%B8%D0%B5%20%E2%84%96TSFS-AGMK-NCR-007.pdf?csf=1&web=1&e=y8YVVO",
    "signed_scan_uploaded_at": "2026-01-31T21:39:45.537875",
    "signed_scan_uploaded_by": "Madiyar Adilzhanov Alikovich",
    "updated_at": "2026-01-31T21:39:45.538329",
    "closed_at": "2026-01-29T23:24:43.015646",
    "closed_by": "Madiyar Adilzhanov"
  },
  {
    "NCR_Number": "TSFS-AGMK-NCR-008",
    "Project": "Освоения месторождения Ешлик-1 Строительства комплекса медно-обогатительной фабрики (МОФ-3) с полным технологическим циклом производства",
    "Contractor": "Enter Engineering Pte. Ltd.",
    "technical_supervisor_company": "Проектный офис  АО “АГМК” ",
    "Discipline": "CIV",
    "major_object": "Пионерная дамба",
    "Draw_number": "Д-3303-П-369078-ХХ",
    "Location": "Западный участок, ПК22+00-23+00",
    "Procedure": "ШНК 3.01.01-03 «Организация строительства», П3.1",
    "NCR_Description": "В ходе операционного контроля на западном участке пионерной дамбы выявлено нарушение технологической последовательности работ. На участке котлована дамбы ПК 22+00 – ПК 23+00, без приёмки предыдущего этапа (котлован не сдан) произведена отсыпка первого слоя насыпи подушки дамбы.",
    "NCR_grade": "Очень важный",
    "inspection_date": "2025-11-20",
    "Correction_acts": "Подрядчику:1.\tПриостановить работы на участке ПК 22+00 – ПК 23+00       2.Демонтаж отсыпанного слоя  3.После устранения замечаний - возобновление работ",
    "closed_date.plan": "2025-11-30",
    "closed_date.actual": "",
    "Measures": "Доработка",
    "inspector_name_field": "Адилжанов М.А",
    "NCR_Status": "Открыто",
    "inspector_id": 4,
    "inspector_name": "Doniyorkhon Rasulov",
    "photos": [
      "ncr_8_1.png"
    ],
    "id": 8,
    "created_at": "2026-01-27 13:46:23",
    "updated_at": "2026-01-29T17:07:00.483224",
    "signed_scan_url": null,
    "signed_scan_uploaded_at": null,
    "signed_scan_uploaded_by": null,
    "closed_at": "2026-01-28T22:41:32.272992",
    "closed_by": "Александр Тен"
  },
  {
    "NCR_Number": "TSFS-AGMK-NCR-0009",
    "Project": "Освоения месторождения Ешлик-1 Строительства комплекса медно-обогатительной фабрики (МОФ-3) с полным технологическим циклом производства",
    "Contractor": "Enter Engineering Pte. Ltd.",
    "technical_supervisor_company": "Проектный офис  АО “АГМК” ",
    "Discipline": "CIV",
    "major_object": "Пионерная дамба",
    "Draw_number": "Д-3303-П-369078 - ХХ",
    "Location": "Западный участок, ПК 06+00 - ПК 08+00",
    "Procedure": "TSFS-EE-000000-CIV-MET-0001",
    "NCR_Description": "В ходе операционного контроля на западном участке пионерной дамбы выявлено нарушение технологической последовательности работ по месту сопряжения участков ПК 6–8 и ПК 8–11 западной дамбы, разница отметок более 2м. настоящее время выполняется наращивание участка ПК 6–8, что приводит к еще большему увеличению разницы по высоте между указанными участками.",
    "NCR_grade": "Очень важный",
    "inspection_date": "2026-02-09",
    "Correction_acts": "Подрядчику необходимо:Выполнить наращивание участка ПК 8–11;Предусмотреть устройство полок (уступов) и конструктивное сопряжение участков;Обеспечить плотное сопряжение слоёв и совместную работу грунта в зоне сопряжения.",
    "closed_date.plan": "2026-02-18",
    "closed_date.actual": "",
    "Measures": "Доработка",
    "inspector_name_field": "Madiyar Adilzhanov Alikovich",
    "NCR_Status": "Открыто",
    "inspector_id": 1,
    "inspector_name": "Madiyar Adilzhanov Alikovich",
    "photos": [
      "ncr_9_1.jpg",
      "ncr_9_2.jpg"
    ],
    "id": 9,
    "created_at": "2026-02-09T21:24:20.828024",
    "updated_at": "2026-02-09T21:28:48.985886"
  }
]